napari_shape_odyssey/__init__.py
napari_shape_odyssey/_reader.py
napari_shape_odyssey/_sample_data.py
napari_shape_odyssey/_utils.py
napari_shape_odyssey/_visualize.py
napari_shape_odyssey/_writer.py
napari_shape_odyssey/napari.yaml
napari_shape_odyssey/_signatures/__init__.py
napari_shape_odyssey/_signatures/landmarks.py
napari_shape_odyssey/_signatures/signatures.py
napari_shape_odyssey/_spectral/__init__.py
napari_shape_odyssey/_spectral/expansion.py
napari_shape_odyssey/_spectral/spectral.py
napari_shape_odyssey/_tests/__init__.py
napari_shape_odyssey/_tests/test_shape_correspondence.py
napari_shape_odyssey/_tests/test_spectral.py
napari_shape_odyssey/_unwrapping/__init__.py
napari_shape_odyssey/_unwrapping/projections.py
napari_shape_odyssey/_unwrapping/unwrap.py
napari_shape_odyssey-0.1.1.dist-info/LICENSE
napari_shape_odyssey-0.1.1.dist-info/METADATA
napari_shape_odyssey-0.1.1.dist-info/WHEEL
napari_shape_odyssey-0.1.1.dist-info/entry_points.txt
napari_shape_odyssey-0.1.1.dist-info/top_level.txt
napari_shape_odyssey-0.1.1.dist-info/RECORD
