Metadata-Version: 2.1
Name: napari-shape-odyssey
Version: 0.1.1
Summary: Analyze shapes of meshes
Author: Johannes Soltwedel
Author-email: johannes_richard.soltwedel@tu-dresden.de
License: BSD-3-Clause
Project-URL: Bug Tracker, https://github.com/jo-mueller/napari-shape-odyssey/issues
Project-URL: Documentation, https://jo-mueller.github.io/napari-shape-odyssey/intro.html
Project-URL: Source Code, https://github.com/jo-mueller/napari-shape-odyssey
Project-URL: User Support, https://github.com/jo-mueller/napari-shape-odyssey/issues
Classifier: Development Status :: 2 - Pre-Alpha
Classifier: Framework :: napari
Classifier: Intended Audience :: Developers
Classifier: License :: OSI Approved :: BSD License
Classifier: Operating System :: OS Independent
Classifier: Programming Language :: Python
Classifier: Programming Language :: Python :: 3
Classifier: Programming Language :: Python :: 3 :: Only
Classifier: Programming Language :: Python :: 3.8
Classifier: Programming Language :: Python :: 3.9
Classifier: Programming Language :: Python :: 3.10
Classifier: Topic :: Scientific/Engineering :: Image Processing
Requires-Python: >=3.8
License-File: LICENSE
Requires-Dist: numpy
Requires-Dist: vedo
Requires-Dist: pandas
Requires-Dist: napari
Requires-Dist: napari-stress
Requires-Dist: napari-process-points-and-surfaces
Requires-Dist: pyfmaps
Provides-Extra: testing
Requires-Dist: tox ; extra == 'testing'
Requires-Dist: pytest ; extra == 'testing'
Requires-Dist: pytest-cov ; extra == 'testing'
Requires-Dist: pytest-qt ; extra == 'testing'
Requires-Dist: PyQt5 ; extra == 'testing'
